gapandas/__init__.py
gapandas/connect.py
gapandas/query.py
gapandas/reports.py
gapandas-1.0.dist-info/LICENSE.txt
gapandas-1.0.dist-info/METADATA
gapandas-1.0.dist-info/WHEEL
gapandas-1.0.dist-info/top_level.txt
gapandas-1.0.dist-info/RECORD
