Metadata-Version: 2.1
Name: gapandas
Version: 1.0
Summary: GAPandas is a Python package for accessing Google Analytics API data using Pandas for use in models, reports or visualisations
Home-page: https://github.com/flyandlure/gapandas
Author: Matt Clarke
Author-email: matt@flyandlure.org
License: MIT
Download-URL: https://github.com/flyandlure/gapandas/archive/master.zip
Keywords: python,google analytics,ga,pandas,universal analytics
Platform: UNKNOWN
Classifier: Development Status :: 3 - Alpha
Classifier: Intended Audience :: Developers
Classifier: Topic :: Software Development :: Libraries :: Python Modules
Classifier: License :: OSI Approved :: MIT License
Classifier: Programming Language :: Python :: 3.6
Requires-Dist: pandas
Requires-Dist: google-api-python-client
Requires-Dist: oauth2client
